carconnectivity_cli/__init__.py
carconnectivity_cli/_version.py
carconnectivity_cli/carconnectivity_cli_base.py
carconnectivity_cli-0.6.dist-info/licenses/LICENSE
carconnectivity_cli-0.6.dist-info/METADATA
carconnectivity_cli-0.6.dist-info/WHEEL
carconnectivity_cli-0.6.dist-info/entry_points.txt
carconnectivity_cli-0.6.dist-info/top_level.txt
carconnectivity_cli-0.6.dist-info/RECORD
