Metadata-Version: 2.4
Name: carconnectivity-cli
Version: 0.6
Summary: Library for retrieving information from car connectivity services
Author: Till Steinbach
License: MIT License
Classifier: Development Status :: 3 - Alpha
Classifier: Environment :: Console
Classifier: License :: OSI Approved :: MIT License
Classifier: Intended Audience :: End Users/Desktop
Classifier: Intended Audience :: System Administrators
Classifier: Programming Language :: Python :: 3.9
Classifier: Programming Language :: Python :: 3.10
Classifier: Programming Language :: Python :: 3.11
Classifier: Programming Language :: Python :: 3.12
Classifier: Programming Language :: Python :: 3.13
Classifier: Topic :: Utilities
Classifier: Topic :: System :: Monitoring
Requires-Python: >=3.9
License-File: LICENSE
Requires-Dist: carconnectivity>=0.7
Requires-Dist: argparse
Requires-Dist: JSON_minify~=0.3.0
Provides-Extra: connectors
Requires-Dist: carconnectivity-connector-volkswagen; extra == "connectors"
Requires-Dist: carconnectivity-connector-skoda; extra == "connectors"
Provides-Extra: plugins
Requires-Dist: carconnectivity-plugin-abrp; extra == "plugins"
Requires-Dist: carconnectivity-plugin-homekit; extra == "plugins"
Dynamic: license-file
